setup.py
khakilet/__init__.py
khakilet/dns.py
khakilet/http.py
khakilet/hub.py
khakilet/lib.py
khakilet/server.py
khakilet/sky.py
khakilet/socket.py
khakilet/stream.py
khakilet/util.py
khakilet/web.py
khakilet.egg-info/PKG-INFO
khakilet.egg-info/SOURCES.txt
khakilet.egg-info/dependency_links.txt
khakilet.egg-info/top_level.txt