Metadata-Version: 1.0
Name: khakilet
Version: 0.2
Summary: Python network library that uses greenlet, libev and libudns
Home-page: http://khakilet.gafol.net
Author: Paul Colomiets
Author-email: pc@gafol.net
License: UNKNOWN
Platform: UNKNOWN
Classifier: Development Status :: 3 - Alpha
Classifier: Programming Language :: Python :: 3
Classifier: License :: OSI Approved :: MIT License
Classifier: Intended Audience :: Developers
Classifier: Topic :: Internet
Classifier: Topic :: Software Development :: Libraries :: Python Modules
Classifier: Programming Language :: Python
